pelican/plugins/pelican_redirect/__init__.py
pelican/plugins/pelican_redirect/_version.py
pelican_redirect-3.0.0.dist-info/METADATA
pelican_redirect-3.0.0.dist-info/WHEEL
pelican_redirect-3.0.0.dist-info/licenses/LICENSE
pelican_redirect-3.0.0.dist-info/RECORD
