Metadata-Version: 2.4
Name: pelican-redirect
Version: 3.0.0
Summary: Redirect pages using meta http-equiv tags
Project-URL: Documentation, https://docs.getpelican.com
Project-URL: Funding, https://donate.getpelican.com/
Project-URL: Homepage, https://github.com/bryanwweber/pelican-redirect
Project-URL: Issues, https://github.com/bryanwweber/pelican-redirect/issues
Project-URL: Source, https://github.com/bryanwweber/pelican-redirect
Author-email: Bryan Weber <bryan.w.weber@gmail.com>, Chris Rose <offline@offby1.net>
License: BSD-3-Clause
License-File: LICENSE
Keywords: html,http-equiv,pelican,plugin,redirect
Classifier: Development Status :: 5 - Production/Stable
Classifier: Environment :: Console
Classifier: Framework :: Pelican
Classifier: Framework :: Pelican :: Plugins
Classifier: Intended Audience :: End Users/Desktop
Classifier: License :: OSI Approved :: BSD License
Classifier: Operating System :: OS Independent
Classifier: Programming Language :: Python :: 3
Classifier: Programming Language :: Python :: 3.10
Classifier: Programming Language :: Python :: 3.11
Classifier: Programming Language :: Python :: 3.12
Classifier: Programming Language :: Python :: 3.13
Classifier: Programming Language :: Python :: 3.14
Classifier: Topic :: Internet :: WWW/HTTP
Classifier: Topic :: Software Development :: Libraries :: Python Modules
Requires-Python: <4.0,>=3.10.0
Requires-Dist: pelican>=4.5
